{"days_day1_types.md":"c341f380","days_day1_vscode.md":"519b8152","days_day2_arraychallenge.md":"4a040978","days_day2_arrays.md":"f7fd50fb","days_day1_vars-template-literals.md":"61566786","days_day2_fizzbuzz.md":"34df3b1c","days_day2_jsloops.md":"d5aabb21","days_day2_logic.md":"e247b832","days_day2_scope.md":"4c2b1735","days_day3_area-calc.md":"942195cf","days_day3_class-objects-challenge.md":"266d5c72","days_day3_functions.md":"f0715b4b","days_day3_jsclass.md":"a8f123df","days_day3_object-this.md":"e10dbd45","days_day4_first-automation.md":"f69369e6","days_day4_page-object-model.md":"d7512e06","days_day4_playwright-installation.md":"6b971e68","days_day4_playwright-tour.md":"d59e5dae","days_day4_text-input-challenge.md":"9512778b","days_day5_class-attribute-scrolls.md":"7def8b53","days_day5_dynamic-table-challenge.md":"3992976c","days_day5_home-page.md":"bba49c0a","days_day5_playwright-mapping.md":"ee0cba91","days_day5_progress-bar-challenge.md":"9c3e8346","days_day5_sample-app-parallel.md":"68287231","days_day6_cloning-branching.md":"4909cd54","days_day6_final-git.md":"9ccfc370","days_day6_git-configuration-and-more.md":"96ab2c9e","days_day6_merge-conflicts.md":"64367751","days_day7_api-snapshots.md":"ef7cb4b5","days_day7_api-start.md":"7b910218","days_day7_json-schema-validation.md":"1effc7a8","days_day7_pokeapi-start.md":"d7eb95bb","days_day7_starter-pokemon.md":"de7d3d5c","days_day7_status-code-validations.md":"99263322","days_day8_api-final.md":"3d807ff0","days_day8_petstore-query-params.md":"6e433bd6","days_day8_post-and-put.md":"679f8b79","days_day2_odd-or-even.md":"7973361d","days_day8_delete.md":"834a7888","days_day9_secrets-and-env.md":"b0a34b59","days_day8_setup-challenge.md":"5469fed4","about_gojo.md":"648fb4d4","days_day8_post-put-challenge.md":"ef5157c2","days_day9_starting-cicd.md":"8ab26772","guide_getting-started.md":"eb12cb46","index.md":"41796826"}
